setup.py
pollen_access/#wallet-rpc-test.py
pollen_access/__init__.py
pollen_access/wallet-rpc-test.py
pollen_access/wallet.py
pollen_access.egg-info/PKG-INFO
pollen_access.egg-info/SOURCES.txt
pollen_access.egg-info/dependency_links.txt
pollen_access.egg-info/not-zip-safe
pollen_access.egg-info/top_level.txt