Metadata-Version: 1.0
Name: pollen-access
Version: 1.0.4
Summary: Python interface for Pollen coin wallet RPC
Home-page: https://github.com/pollen-coin/pollen_access
Author: Pollen Team
Author-email: pollen@example.com
License: MIT
Platform: UNKNOWN
